seed_papertrail/__init__.py
seed_papertrail/config.py
seed_papertrail/decorators.py
seed_papertrail/middleware.py
seed_papertrail-1.5.1.dist-info/top_level.txt
seed_papertrail-1.5.1.dist-info/METADATA
seed_papertrail-1.5.1.dist-info/DESCRIPTION.rst
seed_papertrail-1.5.1.dist-info/metadata.json
seed_papertrail-1.5.1.dist-info/WHEEL
seed_papertrail-1.5.1.dist-info/RECORD
