Metadata-Version: 2.0
Name: seed-papertrail
Version: 1.5.1
Summary: This is the seed-papertrail project.
Home-page: https://github.com/praekeltfoundation/seed-papertrail
Author: Praekelt.org
Author-email: dev@praekelt.org
License: BSD
Keywords: seed papertrail
Platform: UNKNOWN
Classifier: Intended Audience :: Developers
Classifier: Natural Language :: English
Classifier: Programming Language :: Python :: 2.7
Requires-Dist: Django
